{"is_source_file": false, "format": "", "description": "", "external_files": [], "external_methods": [], "published": [], "classes": [], "methods": [], "calls": [], "search-terms": [], "state": 2, "file_id": 2, "knowledge_revision": 69, "git_revision": "b597e076b68997a9d2d825acc5ac08b521fc76a0", "hash": "d1f83b7aea0f420023894b30be2711da", "format-version": 4, "code-base-name": "frontend_lms_app", "filename": "frontend_lms_app/package.json", "revision_history": [{"69": "b597e076b68997a9d2d825acc5ac08b521fc76a0"}]}